cli/__init__.py
cli/ascii_table.py
cli/cli.py
cli/client.py
cli/colors.py
qrshare_io_cli-0.0.5.dist-info/METADATA
qrshare_io_cli-0.0.5.dist-info/WHEEL
qrshare_io_cli-0.0.5.dist-info/entry_points.txt
qrshare_io_cli-0.0.5.dist-info/RECORD
