Metadata-Version: 2.1
Name: qrshare-io-cli
Version: 0.0.5
Summary: A CLI tool for uploading files with https://qrshare.io service
Home-page: https://qrshare.io
Author: Sergey Royz
Author-email: zjor.se@gmail.com
Requires-Python: >=3.8,<4.0
Classifier: Programming Language :: Python :: 3
Classifier: Programming Language :: Python :: 3.8
Classifier: Programming Language :: Python :: 3.9
Classifier: Programming Language :: Python :: 3.10
Classifier: Programming Language :: Python :: 3.11
Requires-Dist: requests (>=2.31.0,<3.0.0)
Project-URL: Repository, https://github.com/zjor/qrshare.io-cli
